plone.portlet.static-4.0.5-py3.13-nspkg.pth
plone/portlet/static/__init__.py
plone/portlet/static/configure.zcml
plone/portlet/static/static.pt
plone/portlet/static/static.py
plone/portlet/static/testing.py
plone/portlet/static/profiles/default/metadata.xml
plone/portlet/static/profiles/default/portlets.xml
plone/portlet/static/tests/__init__.py
plone/portlet/static/tests/test_portlet_static.py
plone_portlet_static-4.0.5.dist-info/METADATA
plone_portlet_static-4.0.5.dist-info/WHEEL
plone_portlet_static-4.0.5.dist-info/entry_points.txt
plone_portlet_static-4.0.5.dist-info/namespace_packages.txt
plone_portlet_static-4.0.5.dist-info/top_level.txt
plone_portlet_static-4.0.5.dist-info/RECORD
